[
  {
    "subject": "SUBJECT",
    "verb": {
      "lemma": "haber",
      "form": "han",
      "tag": "VAIP3P0"
    },
    "clause": "una vez que todos los males se han derramado sobre la faz de la tierra"
  },
  {
    "subject": "SUBJECT",
    "verb": {
      "lemma": "haber",
      "form": "ha",
      "tag": "VAIP3S0"
    },
    "clause": "El partido ha aplazado la muerte del Madrid y precipitado la del Atleti , que recibe un golpe deportivo econ贸mico y psicol贸gico de infinita crueldad"
  },
  {
    "subject": "SUBJECT",
    "verb": {
      "lemma": "recibir",
      "form": "recibe",
      "tag": "VMIP3S0"
    },
    "clause": "que recibe un golpe deportivo econ贸mico y psicol贸gico de infinita crueldad"
  }
]