[
  {
    "subject": "SUBJECT",
    "verb": {
      "lemma": "ser",
      "form": "son",
      "tag": "VSIP3P0"
    },
    "clause": "Estos compuestos son , en consecuencia , sustancias aislantes con valores de conductividad del orden de 10 - 11"
  },
  {
    "subject": "ZERO",
    "verb": {
      "lemma": "mostrar",
      "form": "muestran",
      "tag": "VMIP3P0"
    },
    "clause": "No obstante , sometidos a un dopado oxidante muestran a menudo aumentos sustanciales de la conductividad"
  },
  {
    "subject": "SUBJECT",
    "verb": {
      "lemma": "elevar",
      "form": "eleva",
      "tag": "VMIP3S0"
    },
    "clause": "Así por ejemplo , la ftalocianina de níquel , tras ser - dopada - con yodo , eleva su conductividad de 10 - - a 0,7 S. cm '"
  },
  {
    "subject": "SUBJECT",
    "verb": {
      "lemma": "ser",
      "form": "sería",
      "tag": "VSIC1S0"
    },
    "clause": "lo que sería esencial para asegurar el correcto solapamiento entre orbitales responsables de la conductividad"
  },
  {
    "subject": "ZERO",
    "verb": {
      "lemma": "poder",
      "form": "podríamos",
      "tag": "VMIC1P0"
    },
    "clause": "que en castellano podríamos traducir por - brocheta -"
  },
  {
    "subject": "IMPERSONAL",
    "verb": {
      "lemma": "tratar",
      "form": "trata",
      "tag": "VMIP3S0"
    },
    "clause": "Se trata , en efecto , de introducir un ligando unido al metal del metalomacrociclo"
  }
]