[
    [
        " donde ofreció una conferencia sobre su experiencia política ",
        {
            "form": "ofreció",
            "lemma": "ofrecer",
            "tag": "VMIS3S0"
        }
    ],
    [
        " El mandatario gallego inició ayer una visita oficial a Moscú ,  donde ofreció una conferencia sobre su experiencia política  ",
        {
            "form": "inició",
            "lemma": "iniciar",
            "tag": "VMIS3S0"
        }
    ],
    [
        " que dio , en los años 70 , a las relaciones entre España y la entonces URSS ",
        {
            "form": "dio",
            "lemma": "dar",
            "tag": "VMIS3S0"
        }
    ],
    [
        " EL MINISTRO DE EXTERIORES ruso , Igor Ivanov , agradeció al presidente de la Xunta el impulso  que dio , en los años 70 , a las relaciones entre España y la entonces URSS  ",
        {
            "form": "agradeció",
            "lemma": "agradecer",
            "tag": "VMIS3S0"
        }
    ],
    [
        " Moscú ensalza la labor diplomática de Fraga ",
        {
            "form": "ensalza",
            "lemma": "ensalzar",
            "tag": "VMIP3S0"
        }
    ]
]